rusvm-0.1.1.dist-info/METADATA
rusvm-0.1.1.dist-info/WHEEL
rusvm/__init__.py
rusvm/rusvm.cpython-312-darwin.so
rusvm-0.1.1.dist-info/RECORD
