Metadata-Version: 2.3
Name: rusvm
Version: 0.1.1
Classifier: Programming Language :: Rust
Classifier: Programming Language :: Python :: Implementation :: CPython
Classifier: Programming Language :: Python :: Implementation :: PyPy
Requires-Dist: numpy
Keywords: smo,svm,machine-learning
Author: Nico Strasdat <nstrasdat@gmail.com>
Author-email: Nico Strasdat <nstrasdat@gmail.com>
License: AGPL-3.0-or-later
Requires-Python: >=3.7
Project-URL: Source Code, https://github.com/wotzlaff/rusvm-python
